[
    {
        "@id": "_:genid10",
        "@type": [
            "http://www.w3.org/2000/01/rdf-schema#Datatype"
        ],
        "http://www.w3.org/2002/07/owl#oneOf": [
            {
                "@list": [
                    {
                        "@value": "Cancelled"
                    },
                    {
                        "@value": "Delivered"
                    },
                    {
                        "@value": "InTransit"
                    },
                    {
                        "@value": "PaymentDue"
                    },
                    {
                        "@value": "PickupAvailable"
                    },
                    {
                        "@value": "Problem"
                    },
                    {
                        "@value": "Processing"
                    },
                    {
                        "@value": "Returned"
                    }
                ]
            }
        ]
    },
    {
        "@id": "http://localhost/",
        "@type": [
            "http://cfha.luchs.org/#EntryPoint"
        ],
        "http://cfha.luchs.org/#defaultMediaType": [
            {
                "@value": "application/hal+json"
            },
            {
                "@value": "application/json"
            },
            {
                "@value": "text/html"
            }
        ]
    },
    {
        "@id": "http://localhost/profile/AdditionToShoppingCart",
        "@type": [
            "http://www.w3.org/2002/07/owl#Class"
        ]
    },
    {
        "@id": "http://localhost/profile/Address",
        "@type": [
            "http://www.w3.org/2002/07/owl#Class"
        ]
    },
    {
        "@id": "http://localhost/profile/LineItem",
        "@type": [
            "http://www.w3.org/2002/07/owl#Class"
        ]
    },
    {
        "@id": "http://localhost/profile/Order",
        "@type": [
            "http://www.w3.org/2002/07/owl#Class"
        ]
    },
    {
        "@id": "http://localhost/profile/Orders",
        "@type": [
            "http://www.w3.org/2002/07/owl#Class"
        ]
    },
    {
        "@id": "http://localhost/profile/PaymentOption",
        "@type": [
            "http://www.w3.org/2002/07/owl#Class"
        ]
    },
    {
        "@id": "http://localhost/profile/Product",
        "@type": [
            "http://www.w3.org/2002/07/owl#Class"
        ]
    },
    {
        "@id": "http://localhost/profile/Products",
        "@type": [
            "http://www.w3.org/2002/07/owl#Class"
        ]
    },
    {
        "@id": "http://localhost/profile/QuantityUpdate",
        "@type": [
            "http://www.w3.org/2002/07/owl#Class"
        ],
        "http://cfha.luchs.org/#expectedType": [
            {
                "@id": "http://localhost/profile/QuantityUpdate"
            }
        ],
        "http://cfha.luchs.org/#method": [
            {
                "@value": "PATCH"
            }
        ],
        "http://cfha.luchs.org/#returnedType": [
            {
                "@id": "http://localhost/profile/ShoppingCart"
            }
        ]
    },
    {
        "@id": "http://localhost/profile/ShoppingCart",
        "@type": [
            "http://www.w3.org/2002/07/owl#Class"
        ]
    },
    {
        "@id": "http://localhost/profile/UserProfile",
        "@type": [
            "http://www.w3.org/2002/07/owl#Class"
        ]
    },
    {
        "@id": "http://localhost/profile/accountOwner",
        "@type": [
            "http://www.w3.org/2002/07/owl#DatatypeProperty",
            "http://www.w3.org/2002/07/owl#FunctionalProperty"
        ],
        "http://www.w3.org/2000/01/rdf-schema#domain": [
            {
                "@id": "http://localhost/profile/PaymentOption"
            }
        ],
        "http://www.w3.org/2000/01/rdf-schema#range": [
            {
                "@id": "http://www.w3.org/2001/XMLSchema#string"
            }
        ]
    },
    {
        "@id": "http://localhost/profile/addToShoppingCart",
        "@type": [
            "http://www.w3.org/2002/07/owl#ObjectProperty",
            "http://www.w3.org/2002/07/owl#FunctionalProperty",
            "http://cfha.luchs.org/#Operation"
        ],
        "http://cfha.luchs.org/#expectedType": [
            {
                "@id": "http://localhost/profile/AdditionToShoppingCart"
            }
        ],
        "http://cfha.luchs.org/#method": [
            {
                "@value": "POST"
            }
        ],
        "http://cfha.luchs.org/#returnedType": [
            {
                "@id": "http://localhost/profile/ShoppingCart"
            }
        ]
    },
    {
        "@id": "http://localhost/profile/address",
        "@type": [
            "http://www.w3.org/2002/07/owl#ObjectProperty"
        ],
        "http://www.w3.org/2000/01/rdf-schema#domain": [
            {
                "@id": "http://localhost/profile/UserProfile"
            }
        ],
        "http://www.w3.org/2000/01/rdf-schema#range": [
            {
                "@id": "http://localhost/profile/Address"
            }
        ]
    },
    {
        "@id": "http://localhost/profile/bic",
        "@type": [
            "http://www.w3.org/2002/07/owl#DatatypeProperty",
            "http://www.w3.org/2002/07/owl#FunctionalProperty"
        ],
        "http://www.w3.org/2000/01/rdf-schema#domain": [
            {
                "@id": "http://localhost/profile/PaymentOption"
            }
        ],
        "http://www.w3.org/2000/01/rdf-schema#range": [
            {
                "@id": "http://www.w3.org/2001/XMLSchema#string"
            }
        ]
    },
    {
        "@id": "http://localhost/profile/billingAddress",
        "@type": [
            "http://www.w3.org/2002/07/owl#ObjectProperty",
            "http://www.w3.org/2002/07/owl#FunctionalProperty"
        ],
        "http://www.w3.org/2000/01/rdf-schema#domain": [
            {
                "@id": "http://localhost/profile/Order"
            }
        ],
        "http://www.w3.org/2000/01/rdf-schema#range": [
            {
                "@id": "http://localhost/profile/Address"
            }
        ]
    },
    {
        "@id": "http://localhost/profile/cancel",
        "@type": [
            "http://www.w3.org/2002/07/owl#ObjectProperty",
            "http://www.w3.org/2002/07/owl#FunctionalProperty",
            "http://cfha.luchs.org/#Operation"
        ],
        "http://cfha.luchs.org/#method": [
            {
                "@value": "DELETE"
            }
        ],
        "http://cfha.luchs.org/#returnedType": [
            {
                "@id": "http://localhost/profile/Order"
            }
        ]
    },
    {
        "@id": "http://localhost/profile/city",
        "@type": [
            "http://www.w3.org/2002/07/owl#DatatypeProperty",
            "http://www.w3.org/2002/07/owl#FunctionalProperty"
        ],
        "http://www.w3.org/2000/01/rdf-schema#domain": [
            {
                "@id": "http://localhost/profile/Address"
            }
        ],
        "http://www.w3.org/2000/01/rdf-schema#range": [
            {
                "@id": "http://www.w3.org/2001/XMLSchema#string"
            }
        ]
    },
    {
        "@id": "http://localhost/profile/country",
        "@type": [
            "http://www.w3.org/2002/07/owl#DatatypeProperty",
            "http://www.w3.org/2002/07/owl#FunctionalProperty"
        ],
        "http://www.w3.org/2000/01/rdf-schema#domain": [
            {
                "@id": "http://localhost/profile/Address"
            }
        ],
        "http://www.w3.org/2000/01/rdf-schema#range": [
            {
                "@id": "http://www.w3.org/2001/XMLSchema#string"
            }
        ]
    },
    {
        "@id": "http://localhost/profile/date",
        "@type": [
            "http://www.w3.org/2002/07/owl#DatatypeProperty",
            "http://www.w3.org/2002/07/owl#FunctionalProperty"
        ],
        "http://www.w3.org/2000/01/rdf-schema#domain": [
            {
                "@id": "http://localhost/profile/Order"
            }
        ],
        "http://www.w3.org/2000/01/rdf-schema#range": [
            {
                "@id": "http://www.w3.org/2001/XMLSchema#dateTime"
            }
        ]
    },
    {
        "@id": "http://localhost/profile/description",
        "@type": [
            "http://www.w3.org/2002/07/owl#DatatypeProperty",
            "http://www.w3.org/2002/07/owl#FunctionalProperty"
        ],
        "http://www.w3.org/2000/01/rdf-schema#domain": [
            {
                "@id": "http://localhost/profile/LineItem"
            },
            {
                "@id": "http://localhost/profile/Product"
            }
        ],
        "http://www.w3.org/2000/01/rdf-schema#range": [
            {
                "@id": "http://www.w3.org/2001/XMLSchema#string"
            }
        ]
    },
    {
        "@id": "http://localhost/profile/iban",
        "@type": [
            "http://www.w3.org/2002/07/owl#DatatypeProperty",
            "http://www.w3.org/2002/07/owl#FunctionalProperty"
        ],
        "http://www.w3.org/2000/01/rdf-schema#domain": [
            {
                "@id": "http://localhost/profile/PaymentOption"
            }
        ],
        "http://www.w3.org/2000/01/rdf-schema#range": [
            {
                "@id": "http://www.w3.org/2001/XMLSchema#string"
            }
        ]
    },
    {
        "@id": "http://localhost/profile/image",
        "@type": [
            "http://www.w3.org/2002/07/owl#ObjectProperty",
            "http://www.w3.org/2002/07/owl#FunctionalProperty"
        ],
        "http://www.w3.org/2000/01/rdf-schema#domain": [
            {
                "@id": "http://localhost/profile/Product"
            }
        ]
    },
    {
        "@id": "http://localhost/profile/items",
        "@type": [
            "http://www.w3.org/2002/07/owl#ObjectProperty"
        ],
        "http://www.w3.org/2000/01/rdf-schema#domain": [
            {
                "@id": "http://localhost/profile/Order"
            },
            {
                "@id": "http://localhost/profile/ShoppingCart"
            }
        ],
        "http://www.w3.org/2000/01/rdf-schema#range": [
            {
                "@id": "http://localhost/profile/LineItem"
            }
        ]
    },
    {
        "@id": "http://localhost/profile/name",
        "@type": [
            "http://www.w3.org/2002/07/owl#DatatypeProperty",
            "http://www.w3.org/2002/07/owl#FunctionalProperty"
        ],
        "http://www.w3.org/2000/01/rdf-schema#domain": [
            {
                "@id": "http://localhost/profile/LineItem"
            },
            {
                "@id": "http://localhost/profile/Product"
            }
        ],
        "http://www.w3.org/2000/01/rdf-schema#range": [
            {
                "@id": "http://www.w3.org/2001/XMLSchema#string"
            }
        ]
    },
    {
        "@id": "http://localhost/profile/orderStatus",
        "@type": [
            "http://www.w3.org/2000/01/rdf-schema#Datatype"
        ],
        "http://www.w3.org/2002/07/owl#equivalentClass": [
            {
                "@id": "_:genid10"
            }
        ]
    },
    {
        "@id": "http://localhost/profile/orders",
        "@type": [
            "http://www.w3.org/2002/07/owl#ObjectProperty"
        ],
        "http://www.w3.org/2000/01/rdf-schema#domain": [
            {
                "@id": "http://localhost/profile/Orders"
            }
        ],
        "http://www.w3.org/2000/01/rdf-schema#range": [
            {
                "@id": "http://localhost/profile/Order"
            }
        ]
    },
    {
        "@id": "http://localhost/profile/payment",
        "@type": [
            "http://www.w3.org/2002/07/owl#ObjectProperty",
            "http://www.w3.org/2002/07/owl#FunctionalProperty"
        ],
        "http://www.w3.org/2000/01/rdf-schema#domain": [
            {
                "@id": "http://localhost/profile/Order"
            }
        ],
        "http://www.w3.org/2000/01/rdf-schema#range": [
            {
                "@id": "http://localhost/profile/PaymentOption"
            }
        ]
    },
    {
        "@id": "http://localhost/profile/paymentOption",
        "@type": [
            "http://www.w3.org/2002/07/owl#ObjectProperty"
        ],
        "http://www.w3.org/2000/01/rdf-schema#domain": [
            {
                "@id": "http://localhost/profile/UserProfile"
            }
        ],
        "http://www.w3.org/2000/01/rdf-schema#range": [
            {
                "@id": "http://localhost/profile/PaymentOption"
            }
        ]
    },
    {
        "@id": "http://localhost/profile/placeOrder",
        "@type": [
            "http://www.w3.org/2002/07/owl#ObjectProperty",
            "http://www.w3.org/2002/07/owl#FunctionalProperty",
            "http://cfha.luchs.org/#Operation"
        ],
        "http://cfha.luchs.org/#expectedType": [
            {
                "@id": "http://localhost/profile/Order"
            }
        ],
        "http://cfha.luchs.org/#method": [
            {
                "@value": "POST"
            }
        ],
        "http://cfha.luchs.org/#returnedType": [
            {
                "@id": "http://localhost/profile/Order"
            }
        ]
    },
    {
        "@id": "http://localhost/profile/price",
        "@type": [
            "http://www.w3.org/2002/07/owl#DatatypeProperty",
            "http://www.w3.org/2002/07/owl#FunctionalProperty"
        ],
        "http://www.w3.org/2000/01/rdf-schema#domain": [
            {
                "@id": "http://localhost/profile/LineItem"
            },
            {
                "@id": "http://localhost/profile/Product"
            }
        ],
        "http://www.w3.org/2000/01/rdf-schema#range": [
            {
                "@id": "http://www.w3.org/2001/XMLSchema#decimal"
            }
        ]
    },
    {
        "@id": "http://localhost/profile/product",
        "@type": [
            "http://www.w3.org/2002/07/owl#ObjectProperty",
            "http://www.w3.org/2002/07/owl#FunctionalProperty"
        ],
        "http://www.w3.org/2000/01/rdf-schema#domain": [
            {
                "@id": "http://localhost/profile/AdditionToShoppingCart"
            },
            {
                "@id": "http://localhost/profile/LineItem"
            }
        ],
        "http://www.w3.org/2000/01/rdf-schema#range": [
            {
                "@id": "http://localhost/profile/Product"
            }
        ]
    },
    {
        "@id": "http://localhost/profile/products",
        "@type": [
            "http://www.w3.org/2002/07/owl#ObjectProperty"
        ],
        "http://www.w3.org/2000/01/rdf-schema#domain": [
            {
                "@id": "http://localhost/profile/Products"
            }
        ],
        "http://www.w3.org/2000/01/rdf-schema#range": [
            {
                "@id": "http://localhost/profile/Product"
            }
        ]
    },
    {
        "@id": "http://localhost/profile/quantity",
        "@type": [
            "http://www.w3.org/2002/07/owl#DatatypeProperty",
            "http://www.w3.org/2002/07/owl#FunctionalProperty"
        ],
        "http://www.w3.org/2000/01/rdf-schema#domain": [
            {
                "@id": "http://localhost/profile/AdditionToShoppingCart"
            },
            {
                "@id": "http://localhost/profile/LineItem"
            },
            {
                "@id": "http://localhost/profile/QuantityUpdate"
            }
        ],
        "http://www.w3.org/2000/01/rdf-schema#range": [
            {
                "@id": "http://www.w3.org/2001/XMLSchema#integer"
            }
        ]
    },
    {
        "@id": "http://localhost/profile/remove",
        "@type": [
            "http://www.w3.org/2002/07/owl#ObjectProperty",
            "http://www.w3.org/2002/07/owl#FunctionalProperty",
            "http://cfha.luchs.org/#Operation"
        ],
        "http://cfha.luchs.org/#method": [
            {
                "@value": "DELETE"
            }
        ],
        "http://cfha.luchs.org/#returnedType": [
            {
                "@id": "http://localhost/profile/ShoppingCart"
            }
        ]
    },
    {
        "@id": "http://localhost/profile/shippingAddress",
        "@type": [
            "http://www.w3.org/2002/07/owl#ObjectProperty",
            "http://www.w3.org/2002/07/owl#FunctionalProperty"
        ],
        "http://www.w3.org/2000/01/rdf-schema#domain": [
            {
                "@id": "http://localhost/profile/Order"
            }
        ],
        "http://www.w3.org/2000/01/rdf-schema#range": [
            {
                "@id": "http://localhost/profile/Address"
            }
        ]
    },
    {
        "@id": "http://localhost/profile/status",
        "@type": [
            "http://www.w3.org/2002/07/owl#ObjectProperty",
            "http://www.w3.org/2002/07/owl#FunctionalProperty",
            "http://www.w3.org/2002/07/owl#DatatypeProperty"
        ],
        "http://www.w3.org/2000/01/rdf-schema#domain": [
            {
                "@id": "http://localhost/profile/Order"
            }
        ],
        "http://www.w3.org/2000/01/rdf-schema#range": [
            {
                "@id": "http://localhost/profile/orderStatus"
            }
        ]
    },
    {
        "@id": "http://localhost/profile/street",
        "@type": [
            "http://www.w3.org/2002/07/owl#DatatypeProperty",
            "http://www.w3.org/2002/07/owl#FunctionalProperty"
        ],
        "http://www.w3.org/2000/01/rdf-schema#domain": [
            {
                "@id": "http://localhost/profile/Address"
            }
        ],
        "http://www.w3.org/2000/01/rdf-schema#range": [
            {
                "@id": "http://www.w3.org/2001/XMLSchema#string"
            }
        ],
        "http://www.w3.org/2000/01/rdf-schema#subPropertyOf": [
            {
                "@id": "http://www.w3.org/2002/07/owl#topDataProperty"
            }
        ]
    },
    {
        "@id": "http://localhost/profile/totalPrice",
        "@type": [
            "http://www.w3.org/2002/07/owl#DatatypeProperty",
            "http://www.w3.org/2002/07/owl#FunctionalProperty"
        ],
        "http://www.w3.org/2000/01/rdf-schema#domain": [
            {
                "@id": "http://localhost/profile/ShoppingCart"
            }
        ],
        "http://www.w3.org/2000/01/rdf-schema#range": [
            {
                "@id": "http://www.w3.org/2001/XMLSchema#decimal"
            }
        ]
    },
    {
        "@id": "http://localhost/profile/updateQuantity",
        "@type": [
            "http://www.w3.org/2002/07/owl#ObjectProperty",
            "http://www.w3.org/2002/07/owl#FunctionalProperty",
            "http://cfha.luchs.org/#Operation"
        ],
        "http://cfha.luchs.org/#expectedType": [
            {
                "@id": "http://localhost/profile/QuantityUpdate"
            }
        ],
        "http://cfha.luchs.org/#method": [
            {
                "@value": "PATCH"
            }
        ],
        "http://cfha.luchs.org/#returnedType": [
            {
                "@id": "http://localhost/profile/ShoppingCart"
            }
        ]
    },
    {
        "@id": "http://localhost/profile/zipCode",
        "@type": [
            "http://www.w3.org/2002/07/owl#DatatypeProperty",
            "http://www.w3.org/2002/07/owl#FunctionalProperty"
        ],
        "http://www.w3.org/2000/01/rdf-schema#domain": [
            {
                "@id": "http://localhost/profile/Address"
            }
        ],
        "http://www.w3.org/2000/01/rdf-schema#range": [
            {
                "@id": "http://www.w3.org/2001/XMLSchema#string"
            }
        ],
        "http://www.w3.org/2000/01/rdf-schema#subPropertyOf": [
            {
                "@id": "http://www.w3.org/2002/07/owl#topDataProperty"
            }
        ]
    }
]